fabra/__init__.py
fabra/bus.py
fabra/cli.py
fabra/config.py
fabra/context.py
fabra/core.py
fabra/doctor.py
fabra/embeddings.py
fabra/events.py
fabra/exceptions.py
fabra/graph.py
fabra/hooks.py
fabra/index.py
fabra/models.py
fabra/observability.py
fabra/receipts.py
fabra/retrieval.py
fabra/scheduler.py
fabra/scheduler_dist.py
fabra/server.py
fabra/ui_server.py
fabra/worker.py
fabra/adapters/__init__.py
fabra/adapters/langchain.py
fabra/adapters/openai.py
fabra/demos/__init__.py
fabra/demos/demo_context.py
fabra/demos/demo_features.py
fabra/exporters/__init__.py
fabra/exporters/logging.py
fabra/exporters/otel.py
fabra/store/__init__.py
fabra/store/offline.py
fabra/store/online.py
fabra/store/postgres.py
fabra/store/redis.py
fabra/ui-next/next.config.js
fabra/ui-next/package-lock.json
fabra/ui-next/package.json
fabra/ui-next/postcss.config.js
fabra/ui-next/tailwind.config.ts
fabra/ui-next/tsconfig.json
fabra/ui-next/src/app/globals.css
fabra/ui-next/src/app/layout.tsx
fabra/ui-next/src/app/page.tsx
fabra/ui-next/src/components/ContextDiffPanel.tsx
fabra/ui-next/src/components/ContextResultCard.tsx
fabra/ui-next/src/components/ContextTab.tsx
fabra/ui-next/src/components/FeatureCard.tsx
fabra/ui-next/src/components/JsonViewer.tsx
fabra/ui-next/src/components/LineagePanel.tsx
fabra/ui-next/src/components/MermaidDiagram.tsx
fabra/ui-next/src/components/Sidebar.tsx
fabra/ui-next/src/components/StoreTab.tsx
fabra/ui-next/src/lib/api.ts
fabra/ui-next/src/types/api.ts
fabra/utils/compare.py
fabra/utils/integrity.py
fabra/utils/pricing.py
fabra/utils/signing.py
fabra/utils/snapshots.py
fabra/utils/time.py
fabra/utils/tokens.py
fabra_ai-2.3.3.dist-info/METADATA
fabra_ai-2.3.3.dist-info/WHEEL
fabra_ai-2.3.3.dist-info/entry_points.txt
fabra_ai-2.3.3.dist-info/licenses/LICENSE
fabra_ai-2.3.3.dist-info/RECORD
