Metadata-Version: 2.4
Name: fabra_ai
Version: 2.3.3
Summary: Context infrastructure for AI applications
Project-URL: Homepage, https://github.com/davidahmann/fabra
Project-URL: Repository, https://github.com/davidahmann/fabra
Project-URL: Documentation, https://github.com/davidahmann/fabra#readme
Author-email: Fabra Contributors <dahmann@lumyn.cc>
License: Apache-2.0
License-File: LICENSE
Keywords: data-engineering,feature-store,machine-learning,mlops
Classifier: Development Status :: 3 - Alpha
Classifier: Intended Audience :: Developers
Classifier: License :: OSI Approved :: Apache Software License
Classifier: Programming Language :: Python :: 3
Classifier: Programming Language :: Python :: 3.10
Classifier: Programming Language :: Python :: 3.11
Classifier: Topic :: Scientific/Engineering :: Artificial Intelligence
Requires-Python: >=3.10
Requires-Dist: anthropic>=0.18.0
Requires-Dist: apscheduler>=3.10.0
Requires-Dist: asyncpg>=0.29.0
Requires-Dist: cohere>=4.27.0
Requires-Dist: duckdb>=0.10.0
Requires-Dist: fastapi>=0.100.0
Requires-Dist: greenlet>=3.0.0
Requires-Dist: openai>=2.9.0
Requires-Dist: pandas>=2.0.0
Requires-Dist: pgvector>=0.4.2
Requires-Dist: prometheus-client>=0.17.0
Requires-Dist: psycopg2-binary>=2.9.11
Requires-Dist: pybreaker>=1.0.0
Requires-Dist: pydantic>=2.0.0
Requires-Dist: redis>=5.0.0
Requires-Dist: rich>=13.0.0
Requires-Dist: sqlalchemy[asyncio]>=2.0.0
Requires-Dist: sqlglot>=18.0.0
Requires-Dist: structlog>=23.1.0
Requires-Dist: tiktoken>=0.12.0
Requires-Dist: typer>=0.9.0
Requires-Dist: uuid6>=2024.1.12
Requires-Dist: uvicorn>=0.20.0
Provides-Extra: dev
Requires-Dist: bandit>=1.7.0; extra == 'dev'
Requires-Dist: fakeredis>=2.0.0; extra == 'dev'
Requires-Dist: httpx>=0.24.0; extra == 'dev'
Requires-Dist: mkdocs-material>=9.5.0; extra == 'dev'
Requires-Dist: mkdocs>=1.5.0; extra == 'dev'
Requires-Dist: mypy>=1.0.0; extra == 'dev'
Requires-Dist: pandas-stubs>=2.0.0; extra == 'dev'
Requires-Dist: pre-commit>=3.5.0; extra == 'dev'
Requires-Dist: prometheus-client>=0.17.0; extra == 'dev'
Requires-Dist: pytest-asyncio>=0.23.0; extra == 'dev'
Requires-Dist: pytest-cov>=4.0.0; extra == 'dev'
Requires-Dist: pytest>=7.0.0; extra == 'dev'
Requires-Dist: ruff>=0.1.0; extra == 'dev'
Requires-Dist: testcontainers>=3.7.1; extra == 'dev'
Requires-Dist: types-redis; extra == 'dev'
Requires-Dist: types-sqlalchemy; extra == 'dev'
Provides-Extra: ui
